{"cameraMode":{"drawMode":0,"name":"Shaded","section":"Shading Mode"},"sceneLighting":false,"audioPlay":false,"sceneViewState":{"showFog":true,"showMaterialUpdate":false,"showSkybox":false,"showFlares":true,"showImageEffects":true,"showParticleSystems":true},"in2DMode":false,"pivot":{"x":1.7430238723754883,"y":2.286978244781494,"z":-2.043358564376831},"rotation":{"x":-0.045722782611846927,"y":0.9380694627761841,"z":0.13602444529533387,"w":0.31534522771835329},"size":3.3550519943237306,"orthographic":false}